[
  {
    "Materialid": "10000013-Eye glorify-Mascara ",
    "Materialname": "[彩妆]-[彩妆吧]-[EYES Glorify 2]-假样模块(睫毛膏1假样)",
    "Photopath": "s_Eye glorify-Mascara G 1.jpg",
    "PhotoFullPath": "./content/MaterialImage/s_Eye glorify-Mascara G 1.jpg"
  },
  {
    "Materialid": "10000019-BB Cream tray",
    "Materialname": "[彩妆]-[彩妆吧]-[METEORITES-1]-亲肤BB霜模块",
    "Photopath": "s_BB Cream tray.jpg",
    "PhotoFullPath": "./content/MaterialImage/s_BB Cream tray.jpg"
  },
  {
    "Materialid": "10000019-G603139",
    "Materialname": "[彩妆]-[彩妆吧]-[METEORITES-1]-幻彩流星修颜液模块",
    "Photopath": "s_G603139.jpg",
    "PhotoFullPath": "./content/MaterialImage/s_G603139.jpg"
  },
  {
    "Materialid": "10000019-G604879",
    "Materialname": "[彩妆]-[彩妆吧]-[METEORITES-1]-靓白蜜粉饼遮瑕膏模块",
    "Photopath": "s_G604879.jpg",
    "PhotoFullPath": "http://localhost/Guerlain/content/MaterialImage/s_G604879.jpg"
  },
  {
    "Materialid": "10000019-G604879-cover",
    "Materialname": "[彩妆]-[彩妆吧]-[METEORITES-1]-靓白蜜粉饼遮瑕膏模块盖板",
    "Photopath": "s_G604879-cover.jpg",
    "PhotoFullPath": "./content/MaterialImage/s_G604879-cover.jpg"
  },
  {
    "Materialid": "10000019-G604886",
    "Materialname": "[彩妆]-[彩妆吧]-[METEORITES-1]-幻彩流星豪华粉饼模块",
    "Photopath": "s_G604886.jpg",
    "PhotoFullPath": "./content/MaterialImage/s_G604886.jpg"
  },
  {
    "Materialid": "10000019-G604887",
    "Materialname": "[彩妆]-[彩妆吧]-[METEORITES-1]-幻彩流星粉球模块",
    "Photopath": "s_G604887.jpg",
    "PhotoFullPath": "./content/MaterialImage/s_G604887.jpg"
  },
  {
    "Materialid": "10000019-G604888",
    "Materialname": "[彩妆]-[彩妆吧]-[METEORITES-1]-幻彩流星靓白粉球模块",
    "Photopath": "s_G604888.jpg",
    "PhotoFullPath": "./content/MaterialImage/s_G604888.jpg"
  },
  {
    "Materialid": "10000019-G604974",
    "Materialname": "[彩妆]-[彩妆吧]-[METEORITES-1]-幻彩流星蜜粉饼模块",
    "Photopath": "s_G604974.jpg",
    "PhotoFullPath": "./content/MaterialImage/s_G604974.jpg"
  },
  {
    "Materialid": "10000019-G605239",
    "Materialname": "[彩妆]-[彩妆吧]-[METEORITES-1]-金钻凝露模块",
    "Photopath": "s_G605239.jpg",
    "PhotoFullPath": "./content/MaterialImage/s_G605239.jpg"
  }
]